c4dot5/DecisionTree.py
c4dot5/DecisionTreeClassifier.py
c4dot5/__init__.py
c4dot5/attributes.py
c4dot5/checking.py
c4dot5/decision_tree_utils.py
c4dot5/exceptions.py
c4dot5/extracting_rules.py
c4dot5/filtering.py
c4dot5/node_utils.py
c4dot5/nodes.py
c4dot5/old_DecisionTree.py
c4dot5/predicting.py
c4dot5/predictor.py
c4dot5/rules_extraction.py
c4dot5/rules_extractor.py
c4dot5/splitting.py
c4dot5/training.py
c4dot5/traininghandler.py
c4dot5/visualizer.py
c4dot5/visualizing.py
c4dot5_decision_tree-1.2.1.dist-info/LICENSE
c4dot5_decision_tree-1.2.1.dist-info/METADATA
c4dot5_decision_tree-1.2.1.dist-info/WHEEL
c4dot5_decision_tree-1.2.1.dist-info/top_level.txt
c4dot5_decision_tree-1.2.1.dist-info/RECORD
