Metadata-Version: 2.1
Name: c4dot5-decision-tree
Version: 1.2.1
Summary: Train a decision tree using the C4.5 algorithm by Quinlan
License: MIT
Keywords: decision-tree,machine-learning,C4.5
Classifier: License :: OSI Approved :: MIT License
Classifier: Programming Language :: Python
Classifier: Programming Language :: Python :: 3
Requires-Python: >=3.9
License-File: LICENSE
Requires-Dist: numpy
Requires-Dist: pandas
Requires-Dist: graphviz
Requires-Dist: scikit-learn
Provides-Extra: dev
Requires-Dist: pip-tools ; extra == 'dev'
Requires-Dist: pytest ; extra == 'dev'
